{"success":true,"json":[{"id_seccion":215,"pan":"164","pri":"60","prd":"143","pvem":"32","pt":"21","mc":"24","morena":"318","mas":"28","cqroo":"15","pesqroo":"3","pan_prd_pesqroo":"9","pan_prd":"23","pan_pesqroo":"0","prd_pesqroo":"0","total_pan_prd_pesqroo":"362","pvem_pt_morena":"3","pvem_pt":"1","pvem_morena":"6","pt_morena":"3","total_pvem_pt_morena":"384","cand_ind":"0","no_registrados":"1","nulos":"42","total":"896","porcentaje":"4.6875","esperadas":4,"contabilizadas":4,"capturadas":4,"listado_nominal":"2,529","ln_contabilizadas":2529,"participacion":"35.4290","porc_contabilizadas":"100.0000","porc_capturadas":"100.0000"},{"id_seccion":216,"pan":"73","pri":"37","prd":"51","pvem":"16","pt":"6","mc":"33","morena":"126","mas":"10","cqroo":"14","pesqroo":"5","pan_prd_pesqroo":"9","pan_prd":"13","pan_pesqroo":"1","prd_pesqroo":"0","total_pan_prd_pesqroo":"152","pvem_pt_morena":"5","pvem_pt":"1","pvem_morena":"2","pt_morena":"3","total_pvem_pt_morena":"159","cand_ind":"0","no_registrados":"0","nulos":"21","total":"426","porcentaje":"4.9295","esperadas":2,"contabilizadas":2,"capturadas":2,"listado_nominal":"1,102","ln_contabilizadas":1102,"participacion":"38.6570","porc_contabilizadas":"100.0000","porc_capturadas":"100.0000"},{"id_seccion":217,"pan":"114","pri":"46","prd":"94","pvem":"18","pt":"14","mc":"27","morena":"210","mas":"17","cqroo":"16","pesqroo":"5","pan_prd_pesqroo":"12","pan_prd":"18","pan_pesqroo":"2","prd_pesqroo":"0","total_pan_prd_pesqroo":"258","pvem_pt_morena":"7","pvem_pt":"0","pvem_morena":"3","pt_morena":"4","total_pvem_pt_morena":"256","cand_ind":"0","no_registrados":"1","nulos":"34","total":"642","porcentaje":"5.2959","esperadas":3,"contabilizadas":3,"capturadas":3,"listado_nominal":"2,111","ln_contabilizadas":2111,"participacion":"30.4121","porc_contabilizadas":"100.0000","porc_capturadas":"100.0000"},{"id_seccion":218,"pan":"99","pri":"24","prd":"62","pvem":"19","pt":"11","mc":"18","morena":"209","mas":"6","cqroo":"9","pesqroo":"2","pan_prd_pesqroo":"8","pan_prd":"19","pan_pesqroo":"0","prd_pesqroo":"0","total_pan_prd_pesqroo":"196","pvem_pt_morena":"7","pvem_pt":"1","pvem_morena":"3","pt_morena":"4","total_pvem_pt_morena":"254","cand_ind":"0","no_registrados":"1","nulos":"14","total":"516","porcentaje":"2.7131","esperadas":2,"contabilizadas":2,"capturadas":2,"listado_nominal":"1,285","ln_contabilizadas":1285,"participacion":"40.1556","porc_contabilizadas":"100.0000","porc_capturadas":"100.0000"},{"id_seccion":219,"pan":"98","pri":"26","prd":"52","pvem":"17","pt":"9","mc":"22","morena":"165","mas":"9","cqroo":"12","pesqroo":"5","pan_prd_pesqroo":"7","pan_prd":"17","pan_pesqroo":"0","prd_pesqroo":"1","total_pan_prd_pesqroo":"191","pvem_pt_morena":"0","pvem_pt":"0","pvem_morena":"2","pt_morena":"1","total_pvem_pt_morena":"194","cand_ind":"0","no_registrados":"0","nulos":"13","total":"456","porcentaje":"2.8508","esperadas":2,"contabilizadas":2,"capturadas":2,"listado_nominal":"1,437","ln_contabilizadas":1437,"participacion":"31.7328","porc_contabilizadas":"100.0000","porc_capturadas":"100.0000"},{"id_seccion":220,"pan":"101","pri":"29","prd":"61","pvem":"11","pt":"6","mc":"29","morena":"189","mas":"4","cqroo":"9","pesqroo":"2","pan_prd_pesqroo":"6","pan_prd":"5","pan_pesqroo":"0","prd_pesqroo":"3","total_pan_prd_pesqroo":"177","pvem_pt_morena":"4","pvem_pt":"0","pvem_morena":"3","pt_morena":"0","total_pvem_pt_morena":"213","cand_ind":"0","no_registrados":"0","nulos":"12","total":"474","porcentaje":"2.5316","esperadas":2,"contabilizadas":2,"capturadas":2,"listado_nominal":"1,052","ln_contabilizadas":1052,"participacion":"45.0570","porc_contabilizadas":"100.0000","porc_capturadas":"100.0000"},{"id_seccion":221,"pan":"49","pri":"30","prd":"48","pvem":"14","pt":"0","mc":"37","morena":"152","mas":"3","cqroo":"4","pesqroo":"3","pan_prd_pesqroo":"8","pan_prd":"10","pan_pesqroo":"0","prd_pesqroo":"0","total_pan_prd_pesqroo":"125","pvem_pt_morena":"2","pvem_pt":"0","pvem_morena":"1","pt_morena":"3","total_pvem_pt_morena":"172","cand_ind":"0","no_registrados":"0","nulos":"10","total":"374","porcentaje":"2.6737","esperadas":2,"contabilizadas":2,"capturadas":2,"listado_nominal":"866","ln_contabilizadas":866,"participacion":"43.1871","porc_contabilizadas":"100.0000","porc_capturadas":"100.0000"},{"id_seccion":222,"pan":"102","pri":"37","prd":"71","pvem":"26","pt":"8","mc":"45","morena":"220","mas":"31","cqroo":"10","pesqroo":"4","pan_prd_pesqroo":"6","pan_prd":"16","pan_pesqroo":"1","prd_pesqroo":"0","total_pan_prd_pesqroo":"208","pvem_pt_morena":"3","pvem_pt":"1","pvem_morena":"5","pt_morena":"1","total_pvem_pt_morena":"264","cand_ind":"0","no_registrados":"0","nulos":"22","total":"609","porcentaje":"3.6124","esperadas":3,"contabilizadas":3,"capturadas":3,"listado_nominal":"1,528","ln_contabilizadas":1528,"participacion":"39.8560","porc_contabilizadas":"100.0000","porc_capturadas":"100.0000"},{"id_seccion":223,"pan":"147","pri":"41","prd":"110","pvem":"30","pt":"10","mc":"53","morena":"236","mas":"11","cqroo":"15","pesqroo":"4","pan_prd_pesqroo":"5","pan_prd":"14","pan_pesqroo":"0","prd_pesqroo":"2","total_pan_prd_pesqroo":"290","pvem_pt_morena":"4","pvem_pt":"1","pvem_morena":"2","pt_morena":"0","total_pvem_pt_morena":"283","cand_ind":"0","no_registrados":"0","nulos":"32","total":"717","porcentaje":"4.4630","esperadas":4,"contabilizadas":4,"capturadas":4,"listado_nominal":"2,377","ln_contabilizadas":2377,"participacion":"30.1641","porc_contabilizadas":"100.0000","porc_capturadas":"100.0000"},{"id_seccion":224,"pan":"93","pri":"26","prd":"89","pvem":"15","pt":"5","mc":"42","morena":"109","mas":"7","cqroo":"9","pesqroo":"2","pan_prd_pesqroo":"5","pan_prd":"16","pan_pesqroo":"1","prd_pesqroo":"0","total_pan_prd_pesqroo":"220","pvem_pt_morena":"3","pvem_pt":"0","pvem_morena":"2","pt_morena":"3","total_pvem_pt_morena":"137","cand_ind":"0","no_registrados":"1","nulos":"27","total":"455","porcentaje":"5.9340","esperadas":3,"contabilizadas":3,"capturadas":3,"listado_nominal":"1,512","ln_contabilizadas":1512,"participacion":"30.0926","porc_contabilizadas":"100.0000","porc_capturadas":"100.0000"},{"id_seccion":225,"pan":"95","pri":"30","prd":"91","pvem":"19","pt":"10","mc":"43","morena":"231","mas":"5","cqroo":"2","pesqroo":"13","pan_prd_pesqroo":"6","pan_prd":"14","pan_pesqroo":"1","prd_pesqroo":"1","total_pan_prd_pesqroo":"221","pvem_pt_morena":"0","pvem_pt":"0","pvem_morena":"5","pt_morena":"6","total_pvem_pt_morena":"271","cand_ind":"0","no_registrados":"0","nulos":"26","total":"598","porcentaje":"4.3478","esperadas":3,"contabilizadas":3,"capturadas":3,"listado_nominal":"1,614","ln_contabilizadas":1614,"participacion":"37.0508","porc_contabilizadas":"100.0000","porc_capturadas":"100.0000"},{"id_seccion":226,"pan":"177","pri":"50","prd":"112","pvem":"19","pt":"15","mc":"62","morena":"229","mas":"21","cqroo":"12","pesqroo":"4","pan_prd_pesqroo":"10","pan_prd":"24","pan_pesqroo":"1","prd_pesqroo":"1","total_pan_prd_pesqroo":"338","pvem_pt_morena":"9","pvem_pt":"1","pvem_morena":"4","pt_morena":"3","total_pvem_pt_morena":"280","cand_ind":"0","no_registrados":"0","nulos":"34","total":"788","porcentaje":"4.3147","esperadas":3,"contabilizadas":3,"capturadas":3,"listado_nominal":"2,104","ln_contabilizadas":2104,"participacion":"37.4525","porc_contabilizadas":"100.0000","porc_capturadas":"100.0000"},{"id_seccion":227,"pan":"121","pri":"31","prd":"77","pvem":"11","pt":"21","mc":"73","morena":"237","mas":"2","cqroo":"18","pesqroo":"7","pan_prd_pesqroo":"3","pan_prd":"25","pan_pesqroo":"1","prd_pesqroo":"1","total_pan_prd_pesqroo":"252","pvem_pt_morena":"2","pvem_pt":"0","pvem_morena":"0","pt_morena":"0","total_pvem_pt_morena":"271","cand_ind":"0","no_registrados":"0","nulos":"42","total":"672","porcentaje":"6.2500","esperadas":3,"contabilizadas":3,"capturadas":3,"listado_nominal":"1,778","ln_contabilizadas":1778,"participacion":"37.7953","porc_contabilizadas":"100.0000","porc_capturadas":"100.0000"},{"id_seccion":228,"pan":"108","pri":"36","prd":"58","pvem":"9","pt":"16","mc":"50","morena":"218","mas":"2","cqroo":"11","pesqroo":"9","pan_prd_pesqroo":"6","pan_prd":"22","pan_pesqroo":"0","prd_pesqroo":"0","total_pan_prd_pesqroo":"216","pvem_pt_morena":"1","pvem_pt":"0","pvem_morena":"0","pt_morena":"4","total_pvem_pt_morena":"248","cand_ind":"0","no_registrados":"0","nulos":"20","total":"570","porcentaje":"3.5087","esperadas":2,"contabilizadas":2,"capturadas":2,"listado_nominal":"1,456","ln_contabilizadas":1456,"participacion":"39.1484","porc_contabilizadas":"100.0000","porc_capturadas":"100.0000"},{"id_seccion":229,"pan":"72","pri":"92","prd":"177","pvem":"23","pt":"10","mc":"67","morena":"56","mas":"1","cqroo":"24","pesqroo":"5","pan_prd_pesqroo":"7","pan_prd":"38","pan_pesqroo":"1","prd_pesqroo":"0","total_pan_prd_pesqroo":"333","pvem_pt_morena":"1","pvem_pt":"0","pvem_morena":"0","pt_morena":"0","total_pvem_pt_morena":"90","cand_ind":"0","no_registrados":"0","nulos":"24","total":"598","porcentaje":"4.0133","esperadas":3,"contabilizadas":3,"capturadas":3,"listado_nominal":"1,957","ln_contabilizadas":1957,"participacion":"30.5570","porc_contabilizadas":"100.0000","porc_capturadas":"100.0000"},{"id_seccion":230,"pan":"272","pri":"40","prd":"125","pvem":"7","pt":"12","mc":"5","morena":"45","mas":"25","cqroo":"22","pesqroo":"8","pan_prd_pesqroo":"5","pan_prd":"18","pan_pesqroo":"0","prd_pesqroo":"0","total_pan_prd_pesqroo":"438","pvem_pt_morena":"0","pvem_pt":"0","pvem_morena":"0","pt_morena":"0","total_pvem_pt_morena":"64","cand_ind":"0","no_registrados":"0","nulos":"38","total":"622","porcentaje":"6.1093","esperadas":4,"contabilizadas":3,"capturadas":4,"listado_nominal":"1,791","ln_contabilizadas":1242,"participacion":"34.7292","porc_contabilizadas":"75.0000","porc_capturadas":"100.0000"},{"id_seccion":231,"pan":"58","pri":"20","prd":"55","pvem":"3","pt":"7","mc":"8","morena":"76","mas":"0","cqroo":"15","pesqroo":"4","pan_prd_pesqroo":"5","pan_prd":"7","pan_pesqroo":"0","prd_pesqroo":"1","total_pan_prd_pesqroo":"132","pvem_pt_morena":"0","pvem_pt":"0","pvem_morena":"0","pt_morena":"2","total_pvem_pt_morena":"88","cand_ind":"0","no_registrados":"0","nulos":"19","total":"280","porcentaje":"6.7857","esperadas":3,"contabilizadas":2,"capturadas":3,"listado_nominal":"1,632","ln_contabilizadas":971,"participacion":"17.1569","porc_contabilizadas":"66.6666","porc_capturadas":"100.0000"},{"id_seccion":232,"pan":"145","pri":"40","prd":"111","pvem":"14","pt":"13","mc":"22","morena":"55","mas":"3","cqroo":"17","pesqroo":"8","pan_prd_pesqroo":"0","pan_prd":"3","pan_pesqroo":"9","prd_pesqroo":"1","total_pan_prd_pesqroo":"270","pvem_pt_morena":"1","pvem_pt":"1","pvem_morena":"0","pt_morena":"1","total_pvem_pt_morena":"85","cand_ind":"0","no_registrados":"0","nulos":"30","total":"474","porcentaje":"6.3291","esperadas":3,"contabilizadas":2,"capturadas":3,"listado_nominal":"1,526","ln_contabilizadas":1059,"participacion":"31.0616","porc_contabilizadas":"66.6666","porc_capturadas":"100.0000"},{"id_seccion":233,"pan":"37","pri":"11","prd":"47","pvem":"3","pt":"15","mc":"12","morena":"66","mas":"0","cqroo":"6","pesqroo":"4","pan_prd_pesqroo":"3","pan_prd":"8","pan_pesqroo":"1","prd_pesqroo":"0","total_pan_prd_pesqroo":"104","pvem_pt_morena":"0","pvem_pt":"2","pvem_morena":"0","pt_morena":"0","total_pvem_pt_morena":"86","cand_ind":"0","no_registrados":"0","nulos":"11","total":"226","porcentaje":"4.8672","esperadas":2,"contabilizadas":1,"capturadas":2,"listado_nominal":"1,067","ln_contabilizadas":465,"participacion":"21.1809","porc_contabilizadas":"50.0000","porc_capturadas":"100.0000"},{"id_seccion":234,"pan":"190","pri":"226","prd":"193","pvem":"59","pt":"13","mc":"43","morena":"163","mas":"2","cqroo":"35","pesqroo":"6","pan_prd_pesqroo":"2","pan_prd":"12","pan_pesqroo":"0","prd_pesqroo":"0","total_pan_prd_pesqroo":"402","pvem_pt_morena":"0","pvem_pt":"0","pvem_morena":"0","pt_morena":"0","total_pvem_pt_morena":"235","cand_ind":"0","no_registrados":"1","nulos":"51","total":"996","porcentaje":"5.1204","esperadas":5,"contabilizadas":5,"capturadas":5,"listado_nominal":"2,549","ln_contabilizadas":2549,"participacion":"39.0741","porc_contabilizadas":"100.0000","porc_capturadas":"100.0000"},{"id_seccion":235,"pan":"110","pri":"101","prd":"98","pvem":"16","pt":"16","mc":"19","morena":"136","mas":"7","cqroo":"10","pesqroo":"9","pan_prd_pesqroo":"3","pan_prd":"16","pan_pesqroo":"0","prd_pesqroo":"0","total_pan_prd_pesqroo":"243","pvem_pt_morena":"0","pvem_pt":"0","pvem_morena":"0","pt_morena":"0","total_pvem_pt_morena":"168","cand_ind":"0","no_registrados":"0","nulos":"21","total":"562","porcentaje":"3.7366","esperadas":3,"contabilizadas":3,"capturadas":3,"listado_nominal":"1,656","ln_contabilizadas":1656,"participacion":"33.9372","porc_contabilizadas":"100.0000","porc_capturadas":"100.0000"},{"id_seccion":237,"pan":"61","pri":"108","prd":"156","pvem":"5","pt":"12","mc":"26","morena":"93","mas":"3","cqroo":"7","pesqroo":"8","pan_prd_pesqroo":"10","pan_prd":"7","pan_pesqroo":"0","prd_pesqroo":"0","total_pan_prd_pesqroo":"241","pvem_pt_morena":"0","pvem_pt":"0","pvem_morena":"0","pt_morena":"0","total_pvem_pt_morena":"110","cand_ind":"0","no_registrados":"0","nulos":"15","total":"511","porcentaje":"2.9354","esperadas":2,"contabilizadas":2,"capturadas":2,"listado_nominal":"1,129","ln_contabilizadas":1129,"participacion":"45.2613","porc_contabilizadas":"100.0000","porc_capturadas":"100.0000"},{"id_seccion":238,"pan":"141","pri":"54","prd":"165","pvem":"33","pt":"19","mc":"43","morena":"123","mas":"4","cqroo":"19","pesqroo":"4","pan_prd_pesqroo":"5","pan_prd":"8","pan_pesqroo":"0","prd_pesqroo":"2","total_pan_prd_pesqroo":"327","pvem_pt_morena":"2","pvem_pt":"0","pvem_morena":"0","pt_morena":"3","total_pvem_pt_morena":"180","cand_ind":"0","no_registrados":"0","nulos":"28","total":"653","porcentaje":"4.2879","esperadas":3,"contabilizadas":3,"capturadas":3,"listado_nominal":"1,535","ln_contabilizadas":1535,"participacion":"42.5407","porc_contabilizadas":"100.0000","porc_capturadas":"100.0000"},{"id_seccion":239,"pan":"197","pri":"71","prd":"96","pvem":"18","pt":"17","mc":"42","morena":"142","mas":"5","cqroo":"4","pesqroo":"8","pan_prd_pesqroo":"0","pan_prd":"11","pan_pesqroo":"1","prd_pesqroo":"2","total_pan_prd_pesqroo":"312","pvem_pt_morena":"1","pvem_pt":"1","pvem_morena":"1","pt_morena":"0","total_pvem_pt_morena":"180","cand_ind":"0","no_registrados":"1","nulos":"10","total":"628","porcentaje":"1.5923","esperadas":3,"contabilizadas":3,"capturadas":3,"listado_nominal":"1,504","ln_contabilizadas":1504,"participacion":"41.7553","porc_contabilizadas":"100.0000","porc_capturadas":"100.0000"},{"id_seccion":240,"pan":"43","pri":"25","prd":"72","pvem":"4","pt":"3","mc":"15","morena":"30","mas":"0","cqroo":"7","pesqroo":"0","pan_prd_pesqroo":"0","pan_prd":"1","pan_pesqroo":"0","prd_pesqroo":"0","total_pan_prd_pesqroo":"117","pvem_pt_morena":"0","pvem_pt":"0","pvem_morena":"0","pt_morena":"0","total_pvem_pt_morena":"37","cand_ind":"0","no_registrados":"0","nulos":"5","total":"205","porcentaje":"2.4390","esperadas":2,"contabilizadas":1,"capturadas":2,"listado_nominal":"841","ln_contabilizadas":420,"participacion":"24.3757","porc_contabilizadas":"50.0000","porc_capturadas":"100.0000"},{"id_seccion":241,"pan":"97","pri":"22","prd":"50","pvem":"7","pt":"21","mc":"86","morena":"216","mas":"3","cqroo":"39","pesqroo":"8","pan_prd_pesqroo":"10","pan_prd":"8","pan_pesqroo":"0","prd_pesqroo":"0","total_pan_prd_pesqroo":"173","pvem_pt_morena":"2","pvem_pt":"0","pvem_morena":"1","pt_morena":"3","total_pvem_pt_morena":"250","cand_ind":"0","no_registrados":"0","nulos":"21","total":"594","porcentaje":"3.5353","esperadas":3,"contabilizadas":3,"capturadas":3,"listado_nominal":"1,802","ln_contabilizadas":1802,"participacion":"32.9634","porc_contabilizadas":"100.0000","porc_capturadas":"100.0000"},{"id_seccion":242,"pan":"51","pri":"14","prd":"54","pvem":"9","pt":"10","mc":"36","morena":"115","mas":"1","cqroo":"18","pesqroo":"5","pan_prd_pesqroo":"1","pan_prd":"10","pan_pesqroo":"0","prd_pesqroo":"0","total_pan_prd_pesqroo":"126","pvem_pt_morena":"1","pvem_pt":"0","pvem_morena":"1","pt_morena":"1","total_pvem_pt_morena":"137","cand_ind":"0","no_registrados":"0","nulos":"15","total":"342","porcentaje":"4.3859","esperadas":2,"contabilizadas":2,"capturadas":2,"listado_nominal":"1,251","ln_contabilizadas":1251,"participacion":"27.3381","porc_contabilizadas":"100.0000","porc_capturadas":"100.0000"},{"id_seccion":243,"pan":"16","pri":"54","prd":"36","pvem":"10","pt":"3","mc":"19","morena":"19","mas":"0","cqroo":"9","pesqroo":"1","pan_prd_pesqroo":"0","pan_prd":"2","pan_pesqroo":"1","prd_pesqroo":"0","total_pan_prd_pesqroo":"57","pvem_pt_morena":"0","pvem_pt":"0","pvem_morena":"0","pt_morena":"0","total_pvem_pt_morena":"32","cand_ind":"0","no_registrados":"0","nulos":"9","total":"179","porcentaje":"5.0279","esperadas":1,"contabilizadas":1,"capturadas":1,"listado_nominal":"401","ln_contabilizadas":401,"participacion":"44.6384","porc_contabilizadas":"100.0000","porc_capturadas":"100.0000"},{"id_seccion":244,"pan":"94","pri":"126","prd":"137","pvem":"23","pt":"9","mc":"21","morena":"89","mas":"2","cqroo":"1","pesqroo":"7","pan_prd_pesqroo":"0","pan_prd":"1","pan_pesqroo":"0","prd_pesqroo":"0","total_pan_prd_pesqroo":"233","pvem_pt_morena":"1","pvem_pt":"0","pvem_morena":"0","pt_morena":"0","total_pvem_pt_morena":"122","cand_ind":"0","no_registrados":"0","nulos":"35","total":"546","porcentaje":"6.4102","esperadas":3,"contabilizadas":3,"capturadas":3,"listado_nominal":"1,362","ln_contabilizadas":1362,"participacion":"40.0881","porc_contabilizadas":"100.0000","porc_capturadas":"100.0000"},{"id_seccion":245,"pan":"23","pri":"21","prd":"21","pvem":"4","pt":"1","mc":"22","morena":"65","mas":"22","cqroo":"6","pesqroo":"3","pan_prd_pesqroo":"3","pan_prd":"3","pan_pesqroo":"0","prd_pesqroo":"0","total_pan_prd_pesqroo":"53","pvem_pt_morena":"1","pvem_pt":"1","pvem_morena":"0","pt_morena":"0","total_pvem_pt_morena":"72","cand_ind":"0","no_registrados":"0","nulos":"13","total":"209","porcentaje":"6.2200","esperadas":1,"contabilizadas":1,"capturadas":1,"listado_nominal":"731","ln_contabilizadas":731,"participacion":"28.5910","porc_contabilizadas":"100.0000","porc_capturadas":"100.0000"},{"id_seccion":247,"pan":"191","pri":"133","prd":"81","pvem":"14","pt":"16","mc":"94","morena":"107","mas":"6","cqroo":"22","pesqroo":"3","pan_prd_pesqroo":"3","pan_prd":"9","pan_pesqroo":"0","prd_pesqroo":"0","total_pan_prd_pesqroo":"293","pvem_pt_morena":"1","pvem_pt":"1","pvem_morena":"0","pt_morena":"2","total_pvem_pt_morena":"141","cand_ind":"0","no_registrados":"0","nulos":"57","total":"740","porcentaje":"7.7027","esperadas":4,"contabilizadas":4,"capturadas":4,"listado_nominal":"2,215","ln_contabilizadas":2215,"participacion":"33.4086","porc_contabilizadas":"100.0000","porc_capturadas":"100.0000"},{"id_seccion":248,"pan":"50","pri":"5","prd":"19","pvem":"4","pt":"2","mc":"8","morena":"22","mas":"1","cqroo":"0","pesqroo":"1","pan_prd_pesqroo":"0","pan_prd":"4","pan_pesqroo":"0","prd_pesqroo":"0","total_pan_prd_pesqroo":"77","pvem_pt_morena":"0","pvem_pt":"0","pvem_morena":"0","pt_morena":"0","total_pvem_pt_morena":"28","cand_ind":"0","no_registrados":"0","nulos":"5","total":"121","porcentaje":"4.1322","esperadas":1,"contabilizadas":1,"capturadas":1,"listado_nominal":"497","ln_contabilizadas":497,"participacion":"24.3461","porc_contabilizadas":"100.0000","porc_capturadas":"100.0000"},{"id_seccion":249,"pan":"127","pri":"76","prd":"233","pvem":"23","pt":"21","mc":"97","morena":"62","mas":"0","cqroo":"16","pesqroo":"8","pan_prd_pesqroo":"3","pan_prd":"13","pan_pesqroo":"0","prd_pesqroo":"0","total_pan_prd_pesqroo":"389","pvem_pt_morena":"0","pvem_pt":"1","pvem_morena":"0","pt_morena":"1","total_pvem_pt_morena":"108","cand_ind":"0","no_registrados":"0","nulos":"48","total":"729","porcentaje":"6.5843","esperadas":3,"contabilizadas":3,"capturadas":3,"listado_nominal":"1,989","ln_contabilizadas":1989,"participacion":"36.6516","porc_contabilizadas":"100.0000","porc_capturadas":"100.0000"},{"id_seccion":250,"pan":"74","pri":"86","prd":"234","pvem":"8","pt":"10","mc":"30","morena":"39","mas":"2","cqroo":"1","pesqroo":"4","pan_prd_pesqroo":"4","pan_prd":"20","pan_pesqroo":"0","prd_pesqroo":"0","total_pan_prd_pesqroo":"352","pvem_pt_morena":"0","pvem_pt":"2","pvem_morena":"0","pt_morena":"0","total_pvem_pt_morena":"59","cand_ind":"0","no_registrados":"0","nulos":"39","total":"553","porcentaje":"7.0524","esperadas":2,"contabilizadas":2,"capturadas":2,"listado_nominal":"1,060","ln_contabilizadas":1060,"participacion":"52.1698","porc_contabilizadas":"100.0000","porc_capturadas":"100.0000"},{"id_seccion":251,"pan":"123","pri":"77","prd":"198","pvem":"13","pt":"12","mc":"48","morena":"97","mas":"2","cqroo":"43","pesqroo":"14","pan_prd_pesqroo":"14","pan_prd":"25","pan_pesqroo":"3","prd_pesqroo":"1","total_pan_prd_pesqroo":"388","pvem_pt_morena":"0","pvem_pt":"1","pvem_morena":"0","pt_morena":"0","total_pvem_pt_morena":"123","cand_ind":"0","no_registrados":"0","nulos":"33","total":"704","porcentaje":"4.6875","esperadas":3,"contabilizadas":3,"capturadas":3,"listado_nominal":"1,806","ln_contabilizadas":1806,"participacion":"38.9812","porc_contabilizadas":"100.0000","porc_capturadas":"100.0000"},{"id_seccion":263,"pan":"181","pri":"37","prd":"126","pvem":"10","pt":"23","mc":"54","morena":"287","mas":"15","cqroo":"32","pesqroo":"21","pan_prd_pesqroo":"22","pan_prd":"32","pan_pesqroo":"3","prd_pesqroo":"1","total_pan_prd_pesqroo":"396","pvem_pt_morena":"3","pvem_pt":"1","pvem_morena":"0","pt_morena":"0","total_pvem_pt_morena":"324","cand_ind":"0","no_registrados":"0","nulos":"32","total":"880","porcentaje":"3.6363","esperadas":3,"contabilizadas":3,"capturadas":3,"listado_nominal":"2,144","ln_contabilizadas":2144,"participacion":"41.0448","porc_contabilizadas":"100.0000","porc_capturadas":"100.0000"},{"id_seccion":265,"pan":"211","pri":"47","prd":"188","pvem":"7","pt":"34","mc":"69","morena":"346","mas":"12","cqroo":"16","pesqroo":"40","pan_prd_pesqroo":"46","pan_prd":"43","pan_pesqroo":"1","prd_pesqroo":"1","total_pan_prd_pesqroo":"532","pvem_pt_morena":"5","pvem_pt":"0","pvem_morena":"3","pt_morena":"6","total_pvem_pt_morena":"401","cand_ind":"0","no_registrados":"0","nulos":"36","total":"1111","porcentaje":"3.2403","esperadas":4,"contabilizadas":4,"capturadas":4,"listado_nominal":"2,596","ln_contabilizadas":2596,"participacion":"42.7966","porc_contabilizadas":"100.0000","porc_capturadas":"100.0000"},{"id_seccion":266,"pan":"74","pri":"27","prd":"57","pvem":"2","pt":"8","mc":"23","morena":"127","mas":"3","cqroo":"6","pesqroo":"5","pan_prd_pesqroo":"0","pan_prd":"16","pan_pesqroo":"0","prd_pesqroo":"0","total_pan_prd_pesqroo":"163","pvem_pt_morena":"0","pvem_pt":"0","pvem_morena":"0","pt_morena":"1","total_pvem_pt_morena":"138","cand_ind":"0","no_registrados":"0","nulos":"10","total":"359","porcentaje":"2.7855","esperadas":1,"contabilizadas":1,"capturadas":1,"listado_nominal":"712","ln_contabilizadas":712,"participacion":"50.4213","porc_contabilizadas":"100.0000","porc_capturadas":"100.0000"},{"id_seccion":267,"pan":"41","pri":"30","prd":"70","pvem":"2","pt":"6","mc":"7","morena":"49","mas":"0","cqroo":"1","pesqroo":"8","pan_prd_pesqroo":"2","pan_prd":"15","pan_pesqroo":"1","prd_pesqroo":"13","total_pan_prd_pesqroo":"144","pvem_pt_morena":"1","pvem_pt":"6","pvem_morena":"0","pt_morena":"0","total_pvem_pt_morena":"64","cand_ind":"0","no_registrados":"0","nulos":"15","total":"267","porcentaje":"5.6179","esperadas":2,"contabilizadas":2,"capturadas":2,"listado_nominal":"752","ln_contabilizadas":752,"participacion":"35.5053","porc_contabilizadas":"100.0000","porc_capturadas":"100.0000"},{"id_seccion":268,"pan":"227","pri":"45","prd":"281","pvem":"14","pt":"23","mc":"110","morena":"235","mas":"6","cqroo":"8","pesqroo":"105","pan_prd_pesqroo":"6","pan_prd":"98","pan_pesqroo":"2","prd_pesqroo":"0","total_pan_prd_pesqroo":"669","pvem_pt_morena":"3","pvem_pt":"1","pvem_morena":"1","pt_morena":"2","total_pvem_pt_morena":"279","cand_ind":"0","no_registrados":"0","nulos":"51","total":"1218","porcentaje":"4.1871","esperadas":4,"contabilizadas":4,"capturadas":4,"listado_nominal":"2,439","ln_contabilizadas":2439,"participacion":"49.9385","porc_contabilizadas":"100.0000","porc_capturadas":"100.0000"},{"id_seccion":269,"pan":"41","pri":"15","prd":"85","pvem":"7","pt":"8","mc":"12","morena":"66","mas":"3","cqroo":"1","pesqroo":"19","pan_prd_pesqroo":"1","pan_prd":"17","pan_pesqroo":"1","prd_pesqroo":"1","total_pan_prd_pesqroo":"150","pvem_pt_morena":"0","pvem_pt":"0","pvem_morena":"0","pt_morena":"0","total_pvem_pt_morena":"81","cand_ind":"0","no_registrados":"0","nulos":"9","total":"286","porcentaje":"3.1468","esperadas":2,"contabilizadas":2,"capturadas":2,"listado_nominal":"811","ln_contabilizadas":811,"participacion":"35.2651","porc_contabilizadas":"100.0000","porc_capturadas":"100.0000"},{"id_seccion":272,"pan":"49","pri":"23","prd":"45","pvem":"4","pt":"12","mc":"24","morena":"70","mas":"0","cqroo":"5","pesqroo":"5","pan_prd_pesqroo":"3","pan_prd":"7","pan_pesqroo":"1","prd_pesqroo":"0","total_pan_prd_pesqroo":"112","pvem_pt_morena":"1","pvem_pt":"0","pvem_morena":"1","pt_morena":"0","total_pvem_pt_morena":"88","cand_ind":"0","no_registrados":"0","nulos":"11","total":"261","porcentaje":"4.2145","esperadas":1,"contabilizadas":1,"capturadas":1,"listado_nominal":"646","ln_contabilizadas":646,"participacion":"40.4025","porc_contabilizadas":"100.0000","porc_capturadas":"100.0000"},{"id_seccion":277,"pan":"0","pri":"0","prd":"0","pvem":"0","pt":"0","mc":"0","morena":"0","mas":"0","cqroo":"0","pesqroo":"0","pan_prd_pesqroo":"0","pan_prd":"0","pan_pesqroo":"0","prd_pesqroo":"0","total_pan_prd_pesqroo":"0","pvem_pt_morena":"0","pvem_pt":"0","pvem_morena":"0","pt_morena":"0","total_pvem_pt_morena":"0","cand_ind":"0","no_registrados":"0","nulos":"0","total":"0","porcentaje":"0.0000","esperadas":1,"contabilizadas":0,"capturadas":1,"listado_nominal":"502","ln_contabilizadas":0,"participacion":"0.0000","porc_contabilizadas":"0.0000","porc_capturadas":"100.0000"}]}