{"success":true,"json":[{"id_seccion":15,"pan":"22","pri":"29","prd":"7","pvem":"67","pt":"6","mc":"22","morena":"177","mas":"24","cqroo":"18","pesqroo":"7","pan_prd_pesqroo":"2","pan_prd":"0","pan_pesqroo":"1","prd_pesqroo":"0","total_pan_prd_pesqroo":"32","pvem_pt_morena":"0","pvem_pt":"0","pvem_morena":"2","pt_morena":"1","total_pvem_pt_morena":"253","cand_ind":"0","no_registrados":"2","nulos":"27","total":"414","porcentaje":"6.5217","esperadas":5,"contabilizadas":5,"capturadas":5,"listado_nominal":"3,022","ln_contabilizadas":3022,"participacion":"13.6995","porc_contabilizadas":"100.0000","porc_capturadas":"100.0000"},{"id_seccion":16,"pan":"95","pri":"62","prd":"30","pvem":"155","pt":"19","mc":"67","morena":"440","mas":"46","cqroo":"80","pesqroo":"37","pan_prd_pesqroo":"0","pan_prd":"0","pan_pesqroo":"0","prd_pesqroo":"2","total_pan_prd_pesqroo":"125","pvem_pt_morena":"9","pvem_pt":"2","pvem_morena":"3","pt_morena":"5","total_pvem_pt_morena":"633","cand_ind":"0","no_registrados":"4","nulos":"69","total":"1125","porcentaje":"6.1333","esperadas":12,"contabilizadas":12,"capturadas":12,"listado_nominal":"8,520","ln_contabilizadas":8520,"participacion":"13.2042","porc_contabilizadas":"100.0000","porc_capturadas":"100.0000"},{"id_seccion":18,"pan":"17","pri":"14","prd":"3","pvem":"57","pt":"5","mc":"42","morena":"108","mas":"8","cqroo":"15","pesqroo":"10","pan_prd_pesqroo":"0","pan_prd":"1","pan_pesqroo":"0","prd_pesqroo":"0","total_pan_prd_pesqroo":"22","pvem_pt_morena":"2","pvem_pt":"1","pvem_morena":"4","pt_morena":"10","total_pvem_pt_morena":"187","cand_ind":"0","no_registrados":"0","nulos":"33","total":"330","porcentaje":"10.0000","esperadas":3,"contabilizadas":3,"capturadas":3,"listado_nominal":"1,503","ln_contabilizadas":1503,"participacion":"21.9561","porc_contabilizadas":"100.0000","porc_capturadas":"100.0000"},{"id_seccion":19,"pan":"24","pri":"17","prd":"9","pvem":"65","pt":"16","mc":"25","morena":"148","mas":"4","cqroo":"2","pesqroo":"14","pan_prd_pesqroo":"0","pan_prd":"0","pan_pesqroo":"0","prd_pesqroo":"0","total_pan_prd_pesqroo":"33","pvem_pt_morena":"0","pvem_pt":"0","pvem_morena":"3","pt_morena":"2","total_pvem_pt_morena":"234","cand_ind":"0","no_registrados":"0","nulos":"17","total":"346","porcentaje":"4.9132","esperadas":3,"contabilizadas":3,"capturadas":3,"listado_nominal":"1,583","ln_contabilizadas":1583,"participacion":"21.8572","porc_contabilizadas":"100.0000","porc_capturadas":"100.0000"},{"id_seccion":20,"pan":"23","pri":"28","prd":"6","pvem":"47","pt":"4","mc":"11","morena":"108","mas":"1","cqroo":"9","pesqroo":"9","pan_prd_pesqroo":"0","pan_prd":"0","pan_pesqroo":"0","prd_pesqroo":"0","total_pan_prd_pesqroo":"29","pvem_pt_morena":"2","pvem_pt":"0","pvem_morena":"0","pt_morena":"0","total_pvem_pt_morena":"161","cand_ind":"0","no_registrados":"0","nulos":"12","total":"260","porcentaje":"4.6153","esperadas":2,"contabilizadas":2,"capturadas":2,"listado_nominal":"1,292","ln_contabilizadas":1292,"participacion":"20.1238","porc_contabilizadas":"100.0000","porc_capturadas":"100.0000"},{"id_seccion":46,"pan":"17","pri":"27","prd":"11","pvem":"63","pt":"7","mc":"71","morena":"110","mas":"10","cqroo":"25","pesqroo":"6","pan_prd_pesqroo":"1","pan_prd":"0","pan_pesqroo":"0","prd_pesqroo":"0","total_pan_prd_pesqroo":"29","pvem_pt_morena":"1","pvem_pt":"0","pvem_morena":"3","pt_morena":"0","total_pvem_pt_morena":"184","cand_ind":"0","no_registrados":"0","nulos":"25","total":"377","porcentaje":"6.6312","esperadas":2,"contabilizadas":2,"capturadas":2,"listado_nominal":"1,455","ln_contabilizadas":1455,"participacion":"25.9107","porc_contabilizadas":"100.0000","porc_capturadas":"100.0000"},{"id_seccion":47,"pan":"15","pri":"19","prd":"5","pvem":"22","pt":"11","mc":"63","morena":"44","mas":"15","cqroo":"26","pesqroo":"5","pan_prd_pesqroo":"0","pan_prd":"0","pan_pesqroo":"0","prd_pesqroo":"0","total_pan_prd_pesqroo":"20","pvem_pt_morena":"0","pvem_pt":"0","pvem_morena":"1","pt_morena":"0","total_pvem_pt_morena":"78","cand_ind":"0","no_registrados":"0","nulos":"11","total":"237","porcentaje":"4.6413","esperadas":2,"contabilizadas":2,"capturadas":2,"listado_nominal":"1,348","ln_contabilizadas":1348,"participacion":"17.5816","porc_contabilizadas":"100.0000","porc_capturadas":"100.0000"},{"id_seccion":52,"pan":"16","pri":"18","prd":"5","pvem":"50","pt":"6","mc":"28","morena":"109","mas":"9","cqroo":"12","pesqroo":"8","pan_prd_pesqroo":"0","pan_prd":"1","pan_pesqroo":"2","prd_pesqroo":"0","total_pan_prd_pesqroo":"25","pvem_pt_morena":"1","pvem_pt":"0","pvem_morena":"1","pt_morena":"1","total_pvem_pt_morena":"168","cand_ind":"0","no_registrados":"0","nulos":"24","total":"291","porcentaje":"8.2474","esperadas":2,"contabilizadas":2,"capturadas":2,"listado_nominal":"1,443","ln_contabilizadas":1443,"participacion":"20.1663","porc_contabilizadas":"100.0000","porc_capturadas":"100.0000"},{"id_seccion":53,"pan":"33","pri":"21","prd":"4","pvem":"82","pt":"16","mc":"32","morena":"157","mas":"11","cqroo":"47","pesqroo":"17","pan_prd_pesqroo":"2","pan_prd":"1","pan_pesqroo":"0","prd_pesqroo":"0","total_pan_prd_pesqroo":"41","pvem_pt_morena":"4","pvem_pt":"0","pvem_morena":"0","pt_morena":"3","total_pvem_pt_morena":"262","cand_ind":"0","no_registrados":"0","nulos":"31","total":"461","porcentaje":"6.7245","esperadas":4,"contabilizadas":4,"capturadas":4,"listado_nominal":"2,705","ln_contabilizadas":2705,"participacion":"17.0425","porc_contabilizadas":"100.0000","porc_capturadas":"100.0000"},{"id_seccion":54,"pan":"26","pri":"39","prd":"7","pvem":"46","pt":"10","mc":"26","morena":"233","mas":"14","cqroo":"35","pesqroo":"9","pan_prd_pesqroo":"0","pan_prd":"0","pan_pesqroo":"1","prd_pesqroo":"0","total_pan_prd_pesqroo":"34","pvem_pt_morena":"1","pvem_pt":"0","pvem_morena":"1","pt_morena":"2","total_pvem_pt_morena":"293","cand_ind":"0","no_registrados":"1","nulos":"35","total":"486","porcentaje":"7.2016","esperadas":4,"contabilizadas":4,"capturadas":4,"listado_nominal":"2,576","ln_contabilizadas":2576,"participacion":"18.8665","porc_contabilizadas":"100.0000","porc_capturadas":"100.0000"},{"id_seccion":55,"pan":"17","pri":"20","prd":"5","pvem":"62","pt":"4","mc":"32","morena":"92","mas":"2","cqroo":"8","pesqroo":"4","pan_prd_pesqroo":"4","pan_prd":"2","pan_pesqroo":"1","prd_pesqroo":"0","total_pan_prd_pesqroo":"31","pvem_pt_morena":"0","pvem_pt":"1","pvem_morena":"1","pt_morena":"0","total_pvem_pt_morena":"160","cand_ind":"0","no_registrados":"0","nulos":"23","total":"278","porcentaje":"8.2733","esperadas":2,"contabilizadas":2,"capturadas":2,"listado_nominal":"1,261","ln_contabilizadas":1261,"participacion":"22.0460","porc_contabilizadas":"100.0000","porc_capturadas":"100.0000"},{"id_seccion":56,"pan":"14","pri":"18","prd":"1","pvem":"37","pt":"0","mc":"14","morena":"69","mas":"14","cqroo":"8","pesqroo":"6","pan_prd_pesqroo":"0","pan_prd":"0","pan_pesqroo":"0","prd_pesqroo":"0","total_pan_prd_pesqroo":"15","pvem_pt_morena":"1","pvem_pt":"0","pvem_morena":"0","pt_morena":"1","total_pvem_pt_morena":"108","cand_ind":"0","no_registrados":"0","nulos":"15","total":"198","porcentaje":"7.5757","esperadas":2,"contabilizadas":2,"capturadas":2,"listado_nominal":"1,064","ln_contabilizadas":1064,"participacion":"18.6090","porc_contabilizadas":"100.0000","porc_capturadas":"100.0000"},{"id_seccion":71,"pan":"20","pri":"21","prd":"3","pvem":"38","pt":"11","mc":"12","morena":"96","mas":"7","cqroo":"15","pesqroo":"11","pan_prd_pesqroo":"1","pan_prd":"0","pan_pesqroo":"0","prd_pesqroo":"0","total_pan_prd_pesqroo":"24","pvem_pt_morena":"0","pvem_pt":"0","pvem_morena":"0","pt_morena":"2","total_pvem_pt_morena":"147","cand_ind":"0","no_registrados":"0","nulos":"21","total":"258","porcentaje":"8.1395","esperadas":2,"contabilizadas":2,"capturadas":2,"listado_nominal":"1,427","ln_contabilizadas":1427,"participacion":"18.0799","porc_contabilizadas":"100.0000","porc_capturadas":"100.0000"},{"id_seccion":72,"pan":"15","pri":"23","prd":"10","pvem":"89","pt":"5","mc":"18","morena":"124","mas":"7","cqroo":"28","pesqroo":"18","pan_prd_pesqroo":"2","pan_prd":"1","pan_pesqroo":"0","prd_pesqroo":"0","total_pan_prd_pesqroo":"29","pvem_pt_morena":"3","pvem_pt":"0","pvem_morena":"0","pt_morena":"2","total_pvem_pt_morena":"223","cand_ind":"0","no_registrados":"2","nulos":"22","total":"369","porcentaje":"5.9620","esperadas":3,"contabilizadas":3,"capturadas":3,"listado_nominal":"2,223","ln_contabilizadas":2223,"participacion":"16.5992","porc_contabilizadas":"100.0000","porc_capturadas":"100.0000"},{"id_seccion":73,"pan":"29","pri":"26","prd":"13","pvem":"48","pt":"8","mc":"25","morena":"135","mas":"13","cqroo":"19","pesqroo":"5","pan_prd_pesqroo":"2","pan_prd":"1","pan_pesqroo":"0","prd_pesqroo":"0","total_pan_prd_pesqroo":"46","pvem_pt_morena":"3","pvem_pt":"1","pvem_morena":"5","pt_morena":"3","total_pvem_pt_morena":"203","cand_ind":"0","no_registrados":"0","nulos":"16","total":"352","porcentaje":"4.5454","esperadas":3,"contabilizadas":3,"capturadas":3,"listado_nominal":"2,162","ln_contabilizadas":2162,"participacion":"16.2812","porc_contabilizadas":"100.0000","porc_capturadas":"100.0000"},{"id_seccion":74,"pan":"40","pri":"22","prd":"14","pvem":"49","pt":"8","mc":"46","morena":"157","mas":"8","cqroo":"18","pesqroo":"8","pan_prd_pesqroo":"4","pan_prd":"2","pan_pesqroo":"1","prd_pesqroo":"0","total_pan_prd_pesqroo":"63","pvem_pt_morena":"1","pvem_pt":"2","pvem_morena":"2","pt_morena":"2","total_pvem_pt_morena":"221","cand_ind":"0","no_registrados":"2","nulos":"40","total":"426","porcentaje":"9.3896","esperadas":3,"contabilizadas":3,"capturadas":3,"listado_nominal":"1,592","ln_contabilizadas":1592,"participacion":"26.7588","porc_contabilizadas":"100.0000","porc_capturadas":"100.0000"},{"id_seccion":75,"pan":"27","pri":"12","prd":"4","pvem":"36","pt":"9","mc":"27","morena":"82","mas":"6","cqroo":"18","pesqroo":"6","pan_prd_pesqroo":"2","pan_prd":"2","pan_pesqroo":"0","prd_pesqroo":"1","total_pan_prd_pesqroo":"37","pvem_pt_morena":"1","pvem_pt":"1","pvem_morena":"5","pt_morena":"1","total_pvem_pt_morena":"135","cand_ind":"0","no_registrados":"0","nulos":"18","total":"258","porcentaje":"6.9767","esperadas":2,"contabilizadas":2,"capturadas":2,"listado_nominal":"1,149","ln_contabilizadas":1149,"participacion":"22.4543","porc_contabilizadas":"100.0000","porc_capturadas":"100.0000"},{"id_seccion":101,"pan":"7","pri":"3","prd":"1","pvem":"20","pt":"3","mc":"14","morena":"60","mas":"6","cqroo":"7","pesqroo":"2","pan_prd_pesqroo":"0","pan_prd":"1","pan_pesqroo":"0","prd_pesqroo":"0","total_pan_prd_pesqroo":"10","pvem_pt_morena":"0","pvem_pt":"2","pvem_morena":"3","pt_morena":"1","total_pvem_pt_morena":"89","cand_ind":"0","no_registrados":"1","nulos":"7","total":"138","porcentaje":"5.0724","esperadas":1,"contabilizadas":1,"capturadas":1,"listado_nominal":"733","ln_contabilizadas":733,"participacion":"18.8267","porc_contabilizadas":"100.0000","porc_capturadas":"100.0000"},{"id_seccion":102,"pan":"50","pri":"24","prd":"8","pvem":"30","pt":"5","mc":"14","morena":"132","mas":"19","cqroo":"32","pesqroo":"9","pan_prd_pesqroo":"0","pan_prd":"0","pan_pesqroo":"2","prd_pesqroo":"0","total_pan_prd_pesqroo":"60","pvem_pt_morena":"0","pvem_pt":"0","pvem_morena":"1","pt_morena":"3","total_pvem_pt_morena":"171","cand_ind":"0","no_registrados":"0","nulos":"26","total":"355","porcentaje":"7.3239","esperadas":3,"contabilizadas":3,"capturadas":3,"listado_nominal":"1,818","ln_contabilizadas":1818,"participacion":"19.5270","porc_contabilizadas":"100.0000","porc_capturadas":"100.0000"},{"id_seccion":103,"pan":"18","pri":"6","prd":"4","pvem":"18","pt":"1","mc":"0","morena":"44","mas":"0","cqroo":"2","pesqroo":"4","pan_prd_pesqroo":"0","pan_prd":"0","pan_pesqroo":"0","prd_pesqroo":"0","total_pan_prd_pesqroo":"22","pvem_pt_morena":"0","pvem_pt":"0","pvem_morena":"0","pt_morena":"0","total_pvem_pt_morena":"63","cand_ind":"0","no_registrados":"0","nulos":"2","total":"99","porcentaje":"2.0202","esperadas":1,"contabilizadas":1,"capturadas":1,"listado_nominal":"480","ln_contabilizadas":480,"participacion":"20.6250","porc_contabilizadas":"100.0000","porc_capturadas":"100.0000"},{"id_seccion":104,"pan":"48","pri":"36","prd":"1","pvem":"18","pt":"5","mc":"16","morena":"102","mas":"17","cqroo":"16","pesqroo":"7","pan_prd_pesqroo":"0","pan_prd":"0","pan_pesqroo":"1","prd_pesqroo":"0","total_pan_prd_pesqroo":"50","pvem_pt_morena":"0","pvem_pt":"0","pvem_morena":"0","pt_morena":"0","total_pvem_pt_morena":"125","cand_ind":"0","no_registrados":"3","nulos":"15","total":"285","porcentaje":"5.2631","esperadas":2,"contabilizadas":2,"capturadas":2,"listado_nominal":"1,210","ln_contabilizadas":1210,"participacion":"23.5537","porc_contabilizadas":"100.0000","porc_capturadas":"100.0000"},{"id_seccion":127,"pan":"33","pri":"14","prd":"10","pvem":"45","pt":"6","mc":"11","morena":"128","mas":"8","cqroo":"52","pesqroo":"12","pan_prd_pesqroo":"0","pan_prd":"1","pan_pesqroo":"0","prd_pesqroo":"0","total_pan_prd_pesqroo":"44","pvem_pt_morena":"0","pvem_pt":"0","pvem_morena":"0","pt_morena":"1","total_pvem_pt_morena":"180","cand_ind":"0","no_registrados":"0","nulos":"7","total":"328","porcentaje":"2.1341","esperadas":3,"contabilizadas":3,"capturadas":3,"listado_nominal":"2,208","ln_contabilizadas":2208,"participacion":"14.8551","porc_contabilizadas":"100.0000","porc_capturadas":"100.0000"},{"id_seccion":181,"pan":"56","pri":"43","prd":"12","pvem":"111","pt":"15","mc":"44","morena":"309","mas":"20","cqroo":"58","pesqroo":"29","pan_prd_pesqroo":"1","pan_prd":"0","pan_pesqroo":"0","prd_pesqroo":"2","total_pan_prd_pesqroo":"69","pvem_pt_morena":"1","pvem_pt":"1","pvem_morena":"1","pt_morena":"2","total_pvem_pt_morena":"440","cand_ind":"0","no_registrados":"3","nulos":"43","total":"751","porcentaje":"5.7256","esperadas":8,"contabilizadas":8,"capturadas":8,"listado_nominal":"5,270","ln_contabilizadas":5270,"participacion":"14.2505","porc_contabilizadas":"100.0000","porc_capturadas":"100.0000"},{"id_seccion":540,"pan":"5","pri":"3","prd":"3","pvem":"19","pt":"2","mc":"0","morena":"34","mas":"1","cqroo":"7","pesqroo":"5","pan_prd_pesqroo":"0","pan_prd":"1","pan_pesqroo":"0","prd_pesqroo":"0","total_pan_prd_pesqroo":"10","pvem_pt_morena":"1","pvem_pt":"0","pvem_morena":"1","pt_morena":"0","total_pvem_pt_morena":"57","cand_ind":"0","no_registrados":"0","nulos":"8","total":"90","porcentaje":"8.8888","esperadas":1,"contabilizadas":1,"capturadas":1,"listado_nominal":"541","ln_contabilizadas":541,"participacion":"16.6359","porc_contabilizadas":"100.0000","porc_capturadas":"100.0000"},{"id_seccion":541,"pan":"11","pri":"6","prd":"3","pvem":"20","pt":"7","mc":"4","morena":"58","mas":"6","cqroo":"11","pesqroo":"9","pan_prd_pesqroo":"0","pan_prd":"0","pan_pesqroo":"0","prd_pesqroo":"0","total_pan_prd_pesqroo":"14","pvem_pt_morena":"0","pvem_pt":"0","pvem_morena":"1","pt_morena":"0","total_pvem_pt_morena":"86","cand_ind":"0","no_registrados":"0","nulos":"9","total":"145","porcentaje":"6.2068","esperadas":1,"contabilizadas":1,"capturadas":1,"listado_nominal":"708","ln_contabilizadas":708,"participacion":"20.4802","porc_contabilizadas":"100.0000","porc_capturadas":"100.0000"},{"id_seccion":542,"pan":"3","pri":"8","prd":"5","pvem":"20","pt":"1","mc":"4","morena":"62","mas":"4","cqroo":"15","pesqroo":"9","pan_prd_pesqroo":"0","pan_prd":"0","pan_pesqroo":"0","prd_pesqroo":"0","total_pan_prd_pesqroo":"8","pvem_pt_morena":"1","pvem_pt":"0","pvem_morena":"0","pt_morena":"0","total_pvem_pt_morena":"84","cand_ind":"0","no_registrados":"0","nulos":"14","total":"146","porcentaje":"9.5890","esperadas":2,"contabilizadas":2,"capturadas":2,"listado_nominal":"805","ln_contabilizadas":805,"participacion":"18.1366","porc_contabilizadas":"100.0000","porc_capturadas":"100.0000"},{"id_seccion":554,"pan":"6","pri":"10","prd":"1","pvem":"17","pt":"5","mc":"2","morena":"41","mas":"10","cqroo":"11","pesqroo":"14","pan_prd_pesqroo":"0","pan_prd":"0","pan_pesqroo":"0","prd_pesqroo":"0","total_pan_prd_pesqroo":"7","pvem_pt_morena":"6","pvem_pt":"1","pvem_morena":"0","pt_morena":"2","total_pvem_pt_morena":"72","cand_ind":"0","no_registrados":"1","nulos":"10","total":"137","porcentaje":"7.2992","esperadas":1,"contabilizadas":1,"capturadas":1,"listado_nominal":"686","ln_contabilizadas":686,"participacion":"19.9708","porc_contabilizadas":"100.0000","porc_capturadas":"100.0000"},{"id_seccion":555,"pan":"4","pri":"12","prd":"12","pvem":"11","pt":"1","mc":"6","morena":"47","mas":"2","cqroo":"5","pesqroo":"7","pan_prd_pesqroo":"0","pan_prd":"0","pan_pesqroo":"0","prd_pesqroo":"0","total_pan_prd_pesqroo":"16","pvem_pt_morena":"1","pvem_pt":"0","pvem_morena":"0","pt_morena":"1","total_pvem_pt_morena":"61","cand_ind":"0","no_registrados":"0","nulos":"5","total":"114","porcentaje":"4.3859","esperadas":1,"contabilizadas":1,"capturadas":1,"listado_nominal":"519","ln_contabilizadas":519,"participacion":"21.9653","porc_contabilizadas":"100.0000","porc_capturadas":"100.0000"},{"id_seccion":556,"pan":"12","pri":"12","prd":"18","pvem":"25","pt":"4","mc":"7","morena":"88","mas":"8","cqroo":"15","pesqroo":"7","pan_prd_pesqroo":"0","pan_prd":"0","pan_pesqroo":"0","prd_pesqroo":"0","total_pan_prd_pesqroo":"30","pvem_pt_morena":"1","pvem_pt":"0","pvem_morena":"3","pt_morena":"1","total_pvem_pt_morena":"122","cand_ind":"0","no_registrados":"1","nulos":"15","total":"217","porcentaje":"6.9124","esperadas":2,"contabilizadas":2,"capturadas":2,"listado_nominal":"902","ln_contabilizadas":902,"participacion":"24.0576","porc_contabilizadas":"100.0000","porc_capturadas":"100.0000"},{"id_seccion":557,"pan":"6","pri":"1","prd":"17","pvem":"17","pt":"6","mc":"6","morena":"51","mas":"9","cqroo":"5","pesqroo":"9","pan_prd_pesqroo":"0","pan_prd":"0","pan_pesqroo":"0","prd_pesqroo":"0","total_pan_prd_pesqroo":"23","pvem_pt_morena":"2","pvem_pt":"0","pvem_morena":"2","pt_morena":"0","total_pvem_pt_morena":"78","cand_ind":"0","no_registrados":"0","nulos":"6","total":"137","porcentaje":"4.3795","esperadas":1,"contabilizadas":1,"capturadas":1,"listado_nominal":"619","ln_contabilizadas":619,"participacion":"22.1325","porc_contabilizadas":"100.0000","porc_capturadas":"100.0000"},{"id_seccion":558,"pan":"12","pri":"16","prd":"5","pvem":"35","pt":"2","mc":"5","morena":"27","mas":"20","cqroo":"6","pesqroo":"15","pan_prd_pesqroo":"0","pan_prd":"0","pan_pesqroo":"0","prd_pesqroo":"0","total_pan_prd_pesqroo":"17","pvem_pt_morena":"0","pvem_pt":"0","pvem_morena":"1","pt_morena":"1","total_pvem_pt_morena":"66","cand_ind":"0","no_registrados":"0","nulos":"11","total":"156","porcentaje":"7.0512","esperadas":2,"contabilizadas":2,"capturadas":2,"listado_nominal":"938","ln_contabilizadas":938,"participacion":"16.6311","porc_contabilizadas":"100.0000","porc_capturadas":"100.0000"},{"id_seccion":572,"pan":"8","pri":"6","prd":"6","pvem":"27","pt":"2","mc":"8","morena":"39","mas":"17","cqroo":"8","pesqroo":"0","pan_prd_pesqroo":"0","pan_prd":"0","pan_pesqroo":"0","prd_pesqroo":"0","total_pan_prd_pesqroo":"14","pvem_pt_morena":"0","pvem_pt":"0","pvem_morena":"0","pt_morena":"0","total_pvem_pt_morena":"68","cand_ind":"0","no_registrados":"0","nulos":"4","total":"125","porcentaje":"3.2000","esperadas":1,"contabilizadas":1,"capturadas":1,"listado_nominal":"669","ln_contabilizadas":669,"participacion":"18.6846","porc_contabilizadas":"100.0000","porc_capturadas":"100.0000"},{"id_seccion":573,"pan":"12","pri":"12","prd":"5","pvem":"18","pt":"2","mc":"17","morena":"77","mas":"7","cqroo":"15","pesqroo":"6","pan_prd_pesqroo":"0","pan_prd":"0","pan_pesqroo":"0","prd_pesqroo":"0","total_pan_prd_pesqroo":"17","pvem_pt_morena":"1","pvem_pt":"0","pvem_morena":"0","pt_morena":"0","total_pvem_pt_morena":"98","cand_ind":"0","no_registrados":"2","nulos":"15","total":"189","porcentaje":"7.9365","esperadas":2,"contabilizadas":2,"capturadas":2,"listado_nominal":"851","ln_contabilizadas":851,"participacion":"22.2092","porc_contabilizadas":"100.0000","porc_capturadas":"100.0000"},{"id_seccion":574,"pan":"8","pri":"5","prd":"1","pvem":"11","pt":"3","mc":"5","morena":"34","mas":"3","cqroo":"1","pesqroo":"4","pan_prd_pesqroo":"1","pan_prd":"1","pan_pesqroo":"1","prd_pesqroo":"0","total_pan_prd_pesqroo":"13","pvem_pt_morena":"0","pvem_pt":"0","pvem_morena":"2","pt_morena":"0","total_pvem_pt_morena":"50","cand_ind":"0","no_registrados":"0","nulos":"8","total":"88","porcentaje":"9.0909","esperadas":1,"contabilizadas":1,"capturadas":1,"listado_nominal":"526","ln_contabilizadas":526,"participacion":"16.7300","porc_contabilizadas":"100.0000","porc_capturadas":"100.0000"},{"id_seccion":575,"pan":"13","pri":"9","prd":"3","pvem":"17","pt":"8","mc":"13","morena":"81","mas":"4","cqroo":"5","pesqroo":"5","pan_prd_pesqroo":"0","pan_prd":"0","pan_pesqroo":"0","prd_pesqroo":"0","total_pan_prd_pesqroo":"16","pvem_pt_morena":"0","pvem_pt":"0","pvem_morena":"0","pt_morena":"0","total_pvem_pt_morena":"106","cand_ind":"0","no_registrados":"0","nulos":"14","total":"172","porcentaje":"8.1395","esperadas":2,"contabilizadas":2,"capturadas":2,"listado_nominal":"867","ln_contabilizadas":867,"participacion":"19.8385","porc_contabilizadas":"100.0000","porc_capturadas":"100.0000"},{"id_seccion":576,"pan":"8","pri":"9","prd":"4","pvem":"43","pt":"0","mc":"8","morena":"46","mas":"8","cqroo":"9","pesqroo":"2","pan_prd_pesqroo":"0","pan_prd":"1","pan_pesqroo":"0","prd_pesqroo":"0","total_pan_prd_pesqroo":"14","pvem_pt_morena":"0","pvem_pt":"0","pvem_morena":"2","pt_morena":"1","total_pvem_pt_morena":"92","cand_ind":"0","no_registrados":"0","nulos":"13","total":"154","porcentaje":"8.4415","esperadas":1,"contabilizadas":1,"capturadas":1,"listado_nominal":"705","ln_contabilizadas":705,"participacion":"21.8440","porc_contabilizadas":"100.0000","porc_capturadas":"100.0000"},{"id_seccion":577,"pan":"10","pri":"7","prd":"6","pvem":"30","pt":"1","mc":"6","morena":"57","mas":"0","cqroo":"4","pesqroo":"4","pan_prd_pesqroo":"0","pan_prd":"0","pan_pesqroo":"0","prd_pesqroo":"0","total_pan_prd_pesqroo":"16","pvem_pt_morena":"1","pvem_pt":"0","pvem_morena":"2","pt_morena":"0","total_pvem_pt_morena":"91","cand_ind":"0","no_registrados":"0","nulos":"5","total":"133","porcentaje":"3.7593","esperadas":1,"contabilizadas":1,"capturadas":1,"listado_nominal":"665","ln_contabilizadas":665,"participacion":"20.0000","porc_contabilizadas":"100.0000","porc_capturadas":"100.0000"},{"id_seccion":857,"pan":"14","pri":"6","prd":"3","pvem":"8","pt":"4","mc":"11","morena":"75","mas":"1","cqroo":"12","pesqroo":"8","pan_prd_pesqroo":"0","pan_prd":"0","pan_pesqroo":"0","prd_pesqroo":"0","total_pan_prd_pesqroo":"17","pvem_pt_morena":"1","pvem_pt":"0","pvem_morena":"0","pt_morena":"2","total_pvem_pt_morena":"90","cand_ind":"0","no_registrados":"0","nulos":"9","total":"154","porcentaje":"5.8441","esperadas":2,"contabilizadas":2,"capturadas":2,"listado_nominal":"1,142","ln_contabilizadas":1142,"participacion":"13.4851","porc_contabilizadas":"100.0000","porc_capturadas":"100.0000"},{"id_seccion":859,"pan":"7","pri":"6","prd":"1","pvem":"5","pt":"1","mc":"4","morena":"42","mas":"6","cqroo":"4","pesqroo":"4","pan_prd_pesqroo":"0","pan_prd":"0","pan_pesqroo":"0","prd_pesqroo":"0","total_pan_prd_pesqroo":"8","pvem_pt_morena":"0","pvem_pt":"0","pvem_morena":"0","pt_morena":"0","total_pvem_pt_morena":"48","cand_ind":"0","no_registrados":"0","nulos":"5","total":"85","porcentaje":"5.8823","esperadas":1,"contabilizadas":1,"capturadas":1,"listado_nominal":"634","ln_contabilizadas":634,"participacion":"13.4069","porc_contabilizadas":"100.0000","porc_capturadas":"100.0000"},{"id_seccion":860,"pan":"13","pri":"6","prd":"2","pvem":"17","pt":"5","mc":"15","morena":"67","mas":"2","cqroo":"4","pesqroo":"9","pan_prd_pesqroo":"0","pan_prd":"0","pan_pesqroo":"0","prd_pesqroo":"0","total_pan_prd_pesqroo":"15","pvem_pt_morena":"0","pvem_pt":"0","pvem_morena":"2","pt_morena":"0","total_pvem_pt_morena":"91","cand_ind":"0","no_registrados":"0","nulos":"6","total":"148","porcentaje":"4.0540","esperadas":2,"contabilizadas":2,"capturadas":2,"listado_nominal":"907","ln_contabilizadas":907,"participacion":"16.3175","porc_contabilizadas":"100.0000","porc_capturadas":"100.0000"},{"id_seccion":861,"pan":"13","pri":"7","prd":"1","pvem":"15","pt":"3","mc":"12","morena":"73","mas":"7","cqroo":"3","pesqroo":"6","pan_prd_pesqroo":"2","pan_prd":"0","pan_pesqroo":"0","prd_pesqroo":"0","total_pan_prd_pesqroo":"16","pvem_pt_morena":"0","pvem_pt":"0","pvem_morena":"3","pt_morena":"1","total_pvem_pt_morena":"95","cand_ind":"0","no_registrados":"0","nulos":"8","total":"154","porcentaje":"5.1948","esperadas":2,"contabilizadas":2,"capturadas":2,"listado_nominal":"846","ln_contabilizadas":846,"participacion":"18.2033","porc_contabilizadas":"100.0000","porc_capturadas":"100.0000"},{"id_seccion":862,"pan":"19","pri":"10","prd":"2","pvem":"22","pt":"1","mc":"13","morena":"75","mas":"9","cqroo":"8","pesqroo":"6","pan_prd_pesqroo":"0","pan_prd":"0","pan_pesqroo":"0","prd_pesqroo":"0","total_pan_prd_pesqroo":"21","pvem_pt_morena":"2","pvem_pt":"0","pvem_morena":"1","pt_morena":"0","total_pvem_pt_morena":"101","cand_ind":"0","no_registrados":"0","nulos":"11","total":"179","porcentaje":"6.1452","esperadas":2,"contabilizadas":2,"capturadas":2,"listado_nominal":"1,253","ln_contabilizadas":1253,"participacion":"14.2857","porc_contabilizadas":"100.0000","porc_capturadas":"100.0000"},{"id_seccion":863,"pan":"24","pri":"9","prd":"6","pvem":"29","pt":"9","mc":"15","morena":"75","mas":"2","cqroo":"11","pesqroo":"10","pan_prd_pesqroo":"1","pan_prd":"1","pan_pesqroo":"0","prd_pesqroo":"0","total_pan_prd_pesqroo":"33","pvem_pt_morena":"0","pvem_pt":"0","pvem_morena":"0","pt_morena":"0","total_pvem_pt_morena":"113","cand_ind":"0","no_registrados":"0","nulos":"8","total":"200","porcentaje":"4.0000","esperadas":2,"contabilizadas":2,"capturadas":2,"listado_nominal":"1,196","ln_contabilizadas":1196,"participacion":"16.7224","porc_contabilizadas":"100.0000","porc_capturadas":"100.0000"},{"id_seccion":864,"pan":"7","pri":"2","prd":"0","pvem":"11","pt":"2","mc":"7","morena":"48","mas":"3","cqroo":"5","pesqroo":"1","pan_prd_pesqroo":"0","pan_prd":"0","pan_pesqroo":"0","prd_pesqroo":"0","total_pan_prd_pesqroo":"7","pvem_pt_morena":"0","pvem_pt":"0","pvem_morena":"0","pt_morena":"0","total_pvem_pt_morena":"61","cand_ind":"0","no_registrados":"0","nulos":"6","total":"92","porcentaje":"6.5217","esperadas":1,"contabilizadas":1,"capturadas":1,"listado_nominal":"571","ln_contabilizadas":571,"participacion":"16.1121","porc_contabilizadas":"100.0000","porc_capturadas":"100.0000"},{"id_seccion":865,"pan":"1","pri":"7","prd":"0","pvem":"7","pt":"1","mc":"2","morena":"41","mas":"2","cqroo":"9","pesqroo":"0","pan_prd_pesqroo":"0","pan_prd":"0","pan_pesqroo":"0","prd_pesqroo":"1","total_pan_prd_pesqroo":"1","pvem_pt_morena":"0","pvem_pt":"0","pvem_morena":"1","pt_morena":"0","total_pvem_pt_morena":"50","cand_ind":"0","no_registrados":"0","nulos":"5","total":"77","porcentaje":"6.4935","esperadas":1,"contabilizadas":1,"capturadas":1,"listado_nominal":"561","ln_contabilizadas":561,"participacion":"13.7255","porc_contabilizadas":"100.0000","porc_capturadas":"100.0000"},{"id_seccion":866,"pan":"16","pri":"17","prd":"1","pvem":"29","pt":"4","mc":"7","morena":"76","mas":"3","cqroo":"19","pesqroo":"2","pan_prd_pesqroo":"0","pan_prd":"1","pan_pesqroo":"0","prd_pesqroo":"0","total_pan_prd_pesqroo":"19","pvem_pt_morena":"2","pvem_pt":"0","pvem_morena":"0","pt_morena":"4","total_pvem_pt_morena":"115","cand_ind":"0","no_registrados":"0","nulos":"18","total":"199","porcentaje":"9.0452","esperadas":2,"contabilizadas":2,"capturadas":2,"listado_nominal":"1,107","ln_contabilizadas":1107,"participacion":"17.9765","porc_contabilizadas":"100.0000","porc_capturadas":"100.0000"},{"id_seccion":867,"pan":"17","pri":"6","prd":"2","pvem":"26","pt":"3","mc":"5","morena":"74","mas":"5","cqroo":"10","pesqroo":"7","pan_prd_pesqroo":"0","pan_prd":"0","pan_pesqroo":"0","prd_pesqroo":"0","total_pan_prd_pesqroo":"19","pvem_pt_morena":"1","pvem_pt":"0","pvem_morena":"0","pt_morena":"1","total_pvem_pt_morena":"105","cand_ind":"0","no_registrados":"1","nulos":"6","total":"164","porcentaje":"3.6585","esperadas":2,"contabilizadas":2,"capturadas":2,"listado_nominal":"947","ln_contabilizadas":947,"participacion":"17.3178","porc_contabilizadas":"100.0000","porc_capturadas":"100.0000"},{"id_seccion":868,"pan":"12","pri":"4","prd":"0","pvem":"24","pt":"0","mc":"9","morena":"77","mas":"4","cqroo":"3","pesqroo":"3","pan_prd_pesqroo":"0","pan_prd":"0","pan_pesqroo":"0","prd_pesqroo":"0","total_pan_prd_pesqroo":"12","pvem_pt_morena":"1","pvem_pt":"0","pvem_morena":"1","pt_morena":"0","total_pvem_pt_morena":"103","cand_ind":"0","no_registrados":"0","nulos":"8","total":"146","porcentaje":"5.4794","esperadas":1,"contabilizadas":1,"capturadas":1,"listado_nominal":"742","ln_contabilizadas":742,"participacion":"19.6765","porc_contabilizadas":"100.0000","porc_capturadas":"100.0000"},{"id_seccion":869,"pan":"3","pri":"7","prd":"0","pvem":"6","pt":"0","mc":"2","morena":"35","mas":"4","cqroo":"13","pesqroo":"1","pan_prd_pesqroo":"0","pan_prd":"0","pan_pesqroo":"0","prd_pesqroo":"0","total_pan_prd_pesqroo":"3","pvem_pt_morena":"1","pvem_pt":"0","pvem_morena":"0","pt_morena":"0","total_pvem_pt_morena":"42","cand_ind":"0","no_registrados":"1","nulos":"3","total":"76","porcentaje":"3.9473","esperadas":1,"contabilizadas":1,"capturadas":1,"listado_nominal":"622","ln_contabilizadas":622,"participacion":"12.2186","porc_contabilizadas":"100.0000","porc_capturadas":"100.0000"},{"id_seccion":870,"pan":"1","pri":"5","prd":"0","pvem":"9","pt":"3","mc":"3","morena":"37","mas":"1","cqroo":"7","pesqroo":"4","pan_prd_pesqroo":"0","pan_prd":"0","pan_pesqroo":"0","prd_pesqroo":"0","total_pan_prd_pesqroo":"1","pvem_pt_morena":"0","pvem_pt":"0","pvem_morena":"3","pt_morena":"0","total_pvem_pt_morena":"52","cand_ind":"0","no_registrados":"0","nulos":"1","total":"74","porcentaje":"1.3513","esperadas":1,"contabilizadas":1,"capturadas":1,"listado_nominal":"479","ln_contabilizadas":479,"participacion":"15.4489","porc_contabilizadas":"100.0000","porc_capturadas":"100.0000"},{"id_seccion":871,"pan":"8","pri":"8","prd":"2","pvem":"5","pt":"2","mc":"6","morena":"46","mas":"1","cqroo":"6","pesqroo":"3","pan_prd_pesqroo":"0","pan_prd":"0","pan_pesqroo":"0","prd_pesqroo":"0","total_pan_prd_pesqroo":"10","pvem_pt_morena":"0","pvem_pt":"1","pvem_morena":"1","pt_morena":"0","total_pvem_pt_morena":"55","cand_ind":"0","no_registrados":"0","nulos":"12","total":"101","porcentaje":"11.8811","esperadas":1,"contabilizadas":1,"capturadas":1,"listado_nominal":"454","ln_contabilizadas":454,"participacion":"22.2467","porc_contabilizadas":"100.0000","porc_capturadas":"100.0000"},{"id_seccion":872,"pan":"7","pri":"12","prd":"3","pvem":"16","pt":"2","mc":"14","morena":"75","mas":"7","cqroo":"9","pesqroo":"2","pan_prd_pesqroo":"0","pan_prd":"0","pan_pesqroo":"0","prd_pesqroo":"0","total_pan_prd_pesqroo":"10","pvem_pt_morena":"1","pvem_pt":"0","pvem_morena":"0","pt_morena":"1","total_pvem_pt_morena":"95","cand_ind":"0","no_registrados":"1","nulos":"20","total":"170","porcentaje":"11.7647","esperadas":2,"contabilizadas":2,"capturadas":2,"listado_nominal":"806","ln_contabilizadas":806,"participacion":"21.0918","porc_contabilizadas":"100.0000","porc_capturadas":"100.0000"},{"id_seccion":873,"pan":"4","pri":"8","prd":"1","pvem":"26","pt":"4","mc":"9","morena":"41","mas":"5","cqroo":"8","pesqroo":"2","pan_prd_pesqroo":"0","pan_prd":"0","pan_pesqroo":"0","prd_pesqroo":"0","total_pan_prd_pesqroo":"5","pvem_pt_morena":"1","pvem_pt":"0","pvem_morena":"2","pt_morena":"1","total_pvem_pt_morena":"75","cand_ind":"0","no_registrados":"0","nulos":"6","total":"118","porcentaje":"5.0847","esperadas":1,"contabilizadas":1,"capturadas":1,"listado_nominal":"523","ln_contabilizadas":523,"participacion":"22.5621","porc_contabilizadas":"100.0000","porc_capturadas":"100.0000"}]}