{"success":true,"json":[{"ultimo_corte":"1","partido":"pan","votos":3619,"votos_partido":3513,"total":22413,"votos_coalicion":106,"porcentaje":"16.1468","esperadas":268,"contabilizadas":253,"capturadas":268,"ln_contabilizadas":145555,"listado_nominal":"154,262","participacion_cesp":"15.3983","participacion_sesp":"15.2740","porc_contabilizadas":"94.4029","porc_capturadas":"100.0000"},{"ultimo_corte":"1","partido":"pri","votos":1965,"votos_partido":1965,"total":22413,"votos_coalicion":0,"porcentaje":"8.7672","esperadas":268,"contabilizadas":253,"capturadas":268,"ln_contabilizadas":145555,"listado_nominal":"154,262","participacion_cesp":"15.3983","participacion_sesp":"15.2740","porc_contabilizadas":"94.4029","porc_capturadas":"100.0000"},{"ultimo_corte":"1","partido":"prd","votos":465,"votos_partido":371,"total":22413,"votos_coalicion":94,"porcentaje":"2.0746","esperadas":268,"contabilizadas":253,"capturadas":268,"ln_contabilizadas":145555,"listado_nominal":"154,262","participacion_cesp":"15.3983","participacion_sesp":"15.2740","porc_contabilizadas":"94.4029","porc_capturadas":"100.0000"},{"ultimo_corte":"1","partido":"pvem","votos":579,"votos_partido":551,"total":22413,"votos_coalicion":28,"porcentaje":"2.5833","esperadas":268,"contabilizadas":253,"capturadas":268,"ln_contabilizadas":145555,"listado_nominal":"154,262","participacion_cesp":"15.3983","participacion_sesp":"15.2740","porc_contabilizadas":"94.4029","porc_capturadas":"100.0000"},{"ultimo_corte":"1","partido":"pt","votos":1507,"votos_partido":1451,"total":22413,"votos_coalicion":56,"porcentaje":"6.7237","esperadas":268,"contabilizadas":253,"capturadas":268,"ln_contabilizadas":145555,"listado_nominal":"154,262","participacion_cesp":"15.3983","participacion_sesp":"15.2740","porc_contabilizadas":"94.4029","porc_capturadas":"100.0000"},{"ultimo_corte":"1","partido":"mc","votos":1890,"votos_partido":1890,"total":22413,"votos_coalicion":0,"porcentaje":"8.4326","esperadas":268,"contabilizadas":253,"capturadas":268,"ln_contabilizadas":145555,"listado_nominal":"154,262","participacion_cesp":"15.3983","participacion_sesp":"15.2740","porc_contabilizadas":"94.4029","porc_capturadas":"100.0000"},{"ultimo_corte":"1","partido":"morena","votos":4602,"votos_partido":4546,"total":22413,"votos_coalicion":56,"porcentaje":"20.5327","esperadas":268,"contabilizadas":253,"capturadas":268,"ln_contabilizadas":145555,"listado_nominal":"154,262","participacion_cesp":"15.3983","participacion_sesp":"15.2740","porc_contabilizadas":"94.4029","porc_capturadas":"100.0000"},{"ultimo_corte":"1","partido":"mas","votos":4404,"votos_partido":4404,"total":22413,"votos_coalicion":0,"porcentaje":"19.6493","esperadas":268,"contabilizadas":253,"capturadas":268,"ln_contabilizadas":145555,"listado_nominal":"154,262","participacion_cesp":"15.3983","participacion_sesp":"15.2740","porc_contabilizadas":"94.4029","porc_capturadas":"100.0000"},{"ultimo_corte":"1","partido":"cqroo","votos":959,"votos_partido":959,"total":22413,"votos_coalicion":0,"porcentaje":"4.2787","esperadas":268,"contabilizadas":253,"capturadas":268,"ln_contabilizadas":145555,"listado_nominal":"154,262","participacion_cesp":"15.3983","participacion_sesp":"15.2740","porc_contabilizadas":"94.4029","porc_capturadas":"100.0000"},{"ultimo_corte":"1","partido":"pesqroo","votos":832,"votos_partido":766,"total":22413,"votos_coalicion":66,"porcentaje":"3.7121","esperadas":268,"contabilizadas":253,"capturadas":268,"ln_contabilizadas":145555,"listado_nominal":"154,262","participacion_cesp":"15.3983","participacion_sesp":"15.2740","porc_contabilizadas":"94.4029","porc_capturadas":"100.0000"},{"ultimo_corte":"1","partido":"cand_ind","votos":0,"total":22413,"porcentaje":"0.0000","esperadas":268,"contabilizadas":253,"capturadas":268,"ln_contabilizadas":145555,"listado_nominal":"154,262","participacion_cesp":"15.3983","participacion_sesp":"15.2740","porc_contabilizadas":"94.4029","porc_capturadas":"100.0000"},{"ultimo_corte":"1","partido":"no_registrados","votos":39,"total":22413,"porcentaje":"0.1740","esperadas":268,"contabilizadas":253,"capturadas":268,"ln_contabilizadas":145555,"listado_nominal":"154,262","participacion_cesp":"15.3983","participacion_sesp":"15.2740","porc_contabilizadas":"94.4029","porc_capturadas":"100.0000"},{"ultimo_corte":"1","partido":"nulos","votos":1552,"total":22413,"porcentaje":"6.9245","esperadas":268,"contabilizadas":253,"capturadas":268,"ln_contabilizadas":145555,"listado_nominal":"154,262","participacion_cesp":"15.3983","participacion_sesp":"15.2740","porc_contabilizadas":"94.4029","porc_capturadas":"100.0000"}]}